h5pulsar/__init__.py
h5pulsar/derivative_file.py
h5pulsar/h5format.py
h5pulsar/pulsar.py
h5pulsar-1.0.2.dist-info/LICENSE
h5pulsar-1.0.2.dist-info/METADATA
h5pulsar-1.0.2.dist-info/WHEEL
h5pulsar-1.0.2.dist-info/top_level.txt
h5pulsar-1.0.2.dist-info/RECORD
