Metadata-Version: 2.1
Name: h5pulsar
Version: 1.0.2
Summary: Fork of Anne Archibald's code to add hdf5 to Pulsar objects
Author-email: Aaron Johnson <aaron.johnson@nanograv.org>
Project-URL: Homepage, https://github.com/AaronDJohnson/h5pulsar
Classifier: Programming Language :: Python :: 3
Classifier: License :: OSI Approved :: MIT License
Classifier: Operating System :: OS Independent
Requires-Python: >=3.9
License-File: LICENSE
Requires-Dist: astropy (>=5.3)
Requires-Dist: enterprise-pulsar (>=3.3.2)
Requires-Dist: h5py (>=3.8.0)
Requires-Dist: libstempo (>=2.4.5)
Requires-Dist: numpy (>=1.24.3)
Requires-Dist: pint-pulsar (>=0.9.5)
Requires-Dist: packaging (>=23.1)
Requires-Dist: ephem (>=4.1.4)
